Metadata-Version: 2.1
Name: test-martin
Version: 1.0.0
Summary: Software Engineering assignment for job interview.
Home-page: https://github.com/MartinP96/software_engineer_assignment
Author: MartinP96
Author-email: porenta.martin@gmail.com
Requires-Python: >=3.10,<4.0
Classifier: Programming Language :: Python :: 3
Classifier: Programming Language :: Python :: 3.10
Classifier: Programming Language :: Python :: 3.11
Requires-Dist: pyqt5 (>=5.15.7,<6.0.0)
Requires-Dist: pyqtgraph (>=0.13.1,<0.14.0)
Requires-Dist: pyserial (>=3.5,<4.0)
Project-URL: Repository, https://github.com/MartinP96/software_engineer_assignment
